Workbook

Sheet Overview
A1: Retail Sales Analysis – Excel Project
A2: Author: Saideepak Ramarangula | Tools: Microsoft Excel (IF / nested IF, AND/OR, SUMIFS, COUNTIFS, AVERAGEIFS, conditional formatting, charts)
A4: Business question
A5: A retail company sells online and in stores across 6 Indian cities. Management wants to know:
A6: 1. Which categories and cities bring the most sales?
A7: 2. How much booked revenue is lost through cancelled and returned orders?
A8: 3. Do heavy discounts actually help, or do they lead to more cancellations?
A10: What I did
A11: Step 1 – Data cleaning (sheet "Data"): trimmed extra spaces in names, stored Discount % as a real percentage, rebuilt Gross Sales, Discount Amount and Net Sales as formulas, flagged missing ratings and missing subcategories.
A12: Step 2 – Segmentation with IF / nested IF (sheet "Data", columns S–X): realised sales, order value band, discount band, order outcome, rating check, customer priority.
A13: Step 3 – Conditional formatting (sheet "Data"): above-average orders, lost orders, heavy discounts, rating colour scale, net sales data bars.
A14: Step 4 – Pivot summary (sheet "Pivot Summary"): KPIs plus summaries by category, city, sales channel and discount band, built with SUMIFS / COUNTIFS so they update automatically.
... A21: Practice dataset from the Frontlines Edutech "Business Analytics with AI" course (35 orders, August 2026). Figures in INR.

Sheet Data
A1: Order ID | B1: Order Date | C1: Customer ID | D1: Customer Name | E1: City | F1: Category | G1: Product | H1: Subcategory | I1: Unit Price | J1: Quantity | K1: Discount % | L1: Payment Mode | M1: Sales Channel | N1: Order Status | O1: Customer Rating | P1: Gross Sales | Q1: Discount Amount | R1: Net Sales | S1: Realised Sales | T1: Order Value Band | U1: Discount Band | V1: Order Outcome | W1: Rating Check | X1: Customer Priority
A2: ORD1001 | B2: 46235 | C2: C001 | D2: Charan | E2: Bangalore | F2: Electronics | G2: Wireless Mouse | H2: Accessories | I2: 899 | J2: 2 | K2: 0.05 | L2: UPI | M2: Online | N2: Delivered | O2: 4.5 | P2: =I2*J2 -> 1798 | Q2: =P2*K2 -> 89.9 | R2: =P2-Q2 -> 1708.1 | S2: =IF(OR(N2="Cancelled",N2="Returned"),0,R2) -> 1708.1 | T2: =IF(R2>=4000,"High",IF(R2>=2500,"Medium","Low")) -> Low | U2: =IF(K2>=15%,"15%+",IF(K2>=10%,"10-14%","Under 10%")) -> Under 10% | V2: =IF(OR(N2="Cancelled",N2="Returned"),"Lost",IF(N2="Shipped","In Transit","Completed")) -> Completed | W2: =IF(O2=0,"Missing",IF(O2>=4.5,"Excellent",IF(O2>=4,"Good","Poor"))) -> Excellent | X2: =IF(AND(R2>AVERAGE($R$2:$R$36),O2>=4.5,V2<>"Lost"),"Key Customer",IF(AND(V2="Lost",R2>AVERAGE($R$2:$R$36)),"Win Back",IF(V2="Lost","Follow Up","Regular"))) -> Regular
A3: ORD1002 | B3: 46235 | C3: C002 | D3: Ganapati | E3: Hyderabad | F3: Home & Kitchen | G3: Air Fryer | H3: Kitchen | I3: 5499 | J3: 1 | K3: 0.1 | L3: Card | M3: Online | N3: Delivered | O3: 4.2 | P3: =I3*J3 -> 5499 | Q3: =P3*K3 -> 549.9 | R3: =P3-Q3 -> 4949.1 | S3: =IF(OR(N3="Cancelled",N3="Returned"),0,R3) -> 4949.1 | T3: =IF(R3>=4000,"High",IF(R3>=2500,"Medium","Low")) -> High | U3: =IF(K3>=15%,"15%+",IF(K3>=10%,"10-14%","Under 10%")) -> 10-14% | V3: =IF(OR(N3="Cancelled",N3="Returned"),"Lost",IF(N3="Shipped","In Transit","Completed")) -> Completed | W3: =IF(O3=0,"Missing",IF(O3>=4.5,"Excellent",IF(O3>=4,"Good","Poor"))) -> Good | X3: =IF(AND(R3>AVERAGE($R$2:$R$36),O3>=4.5,V3<>"Lost"),"Key Customer",IF(AND(V3="Lost",R3>AVERAGE($R$2:$R$36)),"Win Back",IF(V3="Lost","Follow Up","Regular"))) -> Regular
A4: ORD1003 | B4: 46236 | C4: C003 | D4: Chandu | E4: Chennai | F4: Fashion | G4: Running Shoes | H4: Footwear | I4: 2999 | J4: 1 | K4: 0.15 | L4: UPI | M4: Store | N4: Delivered | O4: 4.7 | P4: =I4*J4 -> 2999 | Q4: =P4*K4 -> 449.85 | R4: =P4-Q4 -> 2549.15 | S4: =IF(OR(N4="Cancelled",N4="Returned"),0,R4) -> 2549.15 | T4: =IF(R4>=4000,"High",IF(R4>=2500,"Medium","Low")) -> Medium | U4: =IF(K4>=15%,"15%+",IF(K4>=10%,"10-14%","Under 10%")) -> 15%+ | V4: =IF(OR(N4="Cancelled",N4="Returned"),"Lost",IF(N4="Shipped","In Transit","Completed")) -> Completed | W4: =IF(O4=0,"Missing",IF(O4>=4.5,"Excellent",IF(O4>=4,"Good","Poor"))) -> Excellent | X4: =IF(AND(R4>AVERAGE($R$2:$R$36),O4>=4.5,V4<>"Lost"),"Key Customer",IF(AND(V4="Lost",R4>AVERAGE($R$2:$R$36)),"Win Back",IF(V4="Lost","Follow Up","Regular"))) -> Regular
A5: ORD1004 | B5: 46236 | C5: C004 | D5: Dayana | E5: Pune | F5: Grocery | G5: Coffee Beans | H5: Beverages | I5: 650 | J5: 4 | K5: 0.05 | L5: Cash | M5: Store | N5: Cancelled | O5: 4.1 | P5: =I5*J5 -> 2600 | Q5: =P5*K5 -> 130 | R5: =P5-Q5 -> 2470 | S5: =IF(OR(N5="Cancelled",N5="Returned"),0,R5) -> 0 | T5: =IF(R5>=4000,"High",IF(R5>=2500,"Medium","Low")) -> Low | U5: =IF(K5>=15%,"15%+",IF(K5>=10%,"10-14%","Under 10%")) -> Under 10% | V5: =IF(OR(N5="Cancelled",N5="Returned"),"Lost",IF(N5="Shipped","In Transit","Completed")) -> Lost | W5: =IF(O5=0,"Missing",IF(O5>=4.5,"Excellent",IF(O5>=4,"Good","Poor"))) -> Good | X5: =IF(AND(R5>AVERAGE($R$2:$R$36),O5>=4.5,V5<>"Lost"),"Key Customer",IF(AND(V5="Lost",R5>AVERAGE($R$2:$R$36)),"Win Back",IF(V5="Lost","Follow Up","Regular"))) -> Follow Up
A6: ORD1005 | B6: 46237 | C6: C005 | D6: Aruna | E6: Bangalore | F6: Electronics | G6: Bluetooth Speaker | H6: Audio | I6: 2199 | J6: 2 | K6: 0.12 | L6: Card | M6: Online | N6: Cancelled | O6: 4.6 | P6: =I6*J6 -> 4398 | Q6: =P6*K6 -> 527.76 | R6: =P6-Q6 -> 3870.24 | S6: =IF(OR(N6="Cancelled",N6="Returned"),0,R6) -> 0 | T6: =IF(R6>=4000,"High",IF(R6>=2500,"Medium","Low")) -> Medium | U6: =IF(K6>=15%,"15%+",IF(K6>=10%,"10-14%","Under 10%")) -> 10-14% | V6: =IF(OR(N6="Cancelled",N6="Returned"),"Lost",IF(N6="Shipped","In Transit","Completed")) -> Lost | W6: =IF(O6=0,"Missing",IF(O6>=4.5,"Excellent",IF(O6>=4,"Good","Poor"))) -> Excellent | X6: =IF(AND(R6>AVERAGE($R$2:$R$36),O6>=4.5,V6<>"Lost"),"Key Customer",IF(AND(V6="Lost",R6>AVERAGE($R$2:$R$36)),"Win Back",IF(V6="Lost","Follow Up","Regular"))) -> Win Back
A7: ORD1006 | B7: 46237 | C7: C006 | D7: Ramya | E7: Mumbai | F7: Fashion | G7: Denim Jacket | H7: Not Available | I7: 2499 | J7: 1 | K7: 0.2 | L7: UPI | M7: Online | N7: Cancelled | O7: 4 | P7: =I7*J7 -> 2499 | Q7: =P7*K7 -> 499.8 | R7: =P7-Q7 -> 1999.2 | S7: =IF(OR(N7="Cancelled",N7="Returned"),0,R7) -> 0 | T7: =IF(R7>=4000,"High",IF(R7>=2500,"Medium","Low")) -> Low | U7: =IF(K7>=15%,"15%+",IF(K7>=10%,"10-14%","Under 10%")) -> 15%+ | V7: =IF(OR(N7="Cancelled",N7="Returned"),"Lost",IF(N7="Shipped","In Transit","Completed")) -> Lost | W7: =IF(O7=0,"Missing",IF(O7>=4.5,"Excellent",IF(O7>=4,"Good","Poor"))) -> Good | X7: =IF(AND(R7>AVERAGE($R$2:$R$36),O7>=4.5,V7<>"Lost"),"Key Customer",IF(AND(V7="Lost",R7>AVERAGE($R$2:$R$36)),"Win Back",IF(V7="Lost","Follow Up","Regular"))) -> Follow Up
A8: ORD1007 | B8: 46238 | C8: C007 | D8: Yamini | E8: Delhi | F8: Beauty | G8: Face Serum | H8: Not Available | I8: 799 | J8: 3 | K8: 0.08 | L8: Card | M8: Online | N8: Delivered | O8: 4.4 | P8: =I8*J8 -> 2397 | Q8: =P8*K8 -> 191.76 | R8: =P8-Q8 -> 2205.24 | S8: =IF(OR(N8="Cancelled",N8="Returned"),0,R8) -> 2205.24 | T8: =IF(R8>=4000,"High",IF(R8>=2500,"Medium","Low")) -> Low | U8: =IF(K8>=15%,"15%+",IF(K8>=10%,"10-14%","Under 10%")) -> Under 10% | V8: =IF(OR(N8="Cancelled",N8="Returned"),"Lost",IF(N8="Shipped","In Transit","Completed")) -> Completed | W8: =IF(O8=0,"Missing",IF(O8>=4.5,"Excellent",IF(O8>=4,"Good","Poor"))) -> Good | X8: =IF(AND(R8>AVERAGE($R$2:$R$36),O8>=4.5,V8<>"Lost"),"Key Customer",IF(AND(V8="Lost",R8>AVERAGE($R$2:$R$36)),"Win Back",IF(V8="Lost","Follow Up","Regular"))) -> Regular
A9: ORD1008 | B9: 46238 | C9: C008 | D9: Sireesha | E9: Bangalore | F9: Home & Kitchen | G9: Non-Stick Pan | H9: Not Available | I9: 1299 | J9: 2 | K9: 0.1 | L9: UPI | M9: Store | N9: Delivered | O9: 4.3 | P9: =I9*J9 -> 2598 | Q9: =P9*K9 -> 259.8 | R9: =P9-Q9 -> 2338.2 | S9: =IF(OR(N9="Cancelled",N9="Returned"),0,R9) -> 2338.2 | T9: =IF(R9>=4000,"High",IF(R9>=2500,"Medium","Low")) -> Low | U9: =IF(K9>=15%,"15%+",IF(K9>=10%,"10-14%","Under 10%")) -> 10-14% | V9: =IF(OR(N9="Cancelled",N9="Returned"),"Lost",IF(N9="Shipped","In Transit","Completed")) -> Completed | W9: =IF(O9=0,"Missing",IF(O9>=4.5,"Excellent",IF(O9>=4,"Good","Poor"))) -> Good | X9: =IF(AND(R9>AVERAGE($R$2:$R$36),O9>=4.5,V9<>"Lost"),"Key Customer",IF(AND(V9="Lost",R9>AVERAGE($R$2:$R$36)),"Win Back",IF(V9="Lost","Follow Up","Regular"))) -> Regular
A10: ORD1009 | B10: 46239 | C10: C009 | D10: Bhagya | E10: Hyderabad | F10: Electronics | G10: Power Bank | H10: Not Available | I10: 1499 | J10: 1 | K10: 0.18 | L10: Card | M10: Online | N10: Shipped | O10: 3.9 | P10: =I10*J10 -> 1499 | Q10: =P10*K10 -> 269.82 | R10: =P10-Q10 -> 1229.18 | S10: =IF(OR(N10="Cancelled",N10="Returned"),0,R10) -> 1229.18 | T10: =IF(R10>=4000,"High",IF(R10>=2500,"Medium","Low")) -> Low | U10: =IF(K10>=15%,"15%+",IF(K10>=10%,"10-14%","Under 10%")) -> 15%+ | V10: =IF(OR(N10="Cancelled",N10="Returned"),"Lost",IF(N10="Shipped","In Transit","Completed")) -> In Transit | W10: =IF(O10=0,"Missing",IF(O10>=4.5,"Excellent",IF(O10>=4,"Good","Poor"))) -> Poor | X10: =IF(AND(R10>AVERAGE($R$2:$R$36),O10>=4.5,V10<>"Lost"),"Key Customer",IF(AND(V10="Lost",R10>AVERAGE($R$2:$R$36)),"Win Back",IF(V10="Lost","Follow Up","Regular"))) -> Regular
A11: ORD1010 | B11: 46239 | C11: C010 | D11: Satwika | E11: Chennai | F11: Grocery | G11: Olive Oil | H11: Not Available | I11: 899 | J11: 3 | K11: 0.06 | L11: Cash | M11: Store | N11: Delivered | O11: 4 | P11: =I11*J11 -> 2697 | Q11: =P11*K11 -> 161.82 | R11: =P11-Q11 -> 2535.18 | S11: =IF(OR(N11="Cancelled",N11="Returned"),0,R11) -> 2535.18 | T11: =IF(R11>=4000,"High",IF(R11>=2500,"Medium","Low")) -> Medium | U11: =IF(K11>=15%,"15%+",IF(K11>=10%,"10-14%","Under 10%")) -> Under 10% | V11: =IF(OR(N11="Cancelled",N11="Returned"),"Lost",IF(N11="Shipped","In Transit","Completed")) -> Completed | W11: =IF(O11=0,"Missing",IF(O11>=4.5,"Excellent",IF(O11>=4,"Good","Poor"))) -> Good | X11: =IF(AND(R11>AVERAGE($R$2:$R$36),O11>=4.5,V11<>"Lost"),"Key Customer",IF(AND(V11="Lost",R11>AVERAGE($R$2:$R$36)),"Win Back",IF(V11="Lost","Follow Up","Regular"))) -> Regular
A12: ORD1011 | B12: 46240 | C12: C011 | D12: Esther | E12: Pune | F12: Fashion | G12: Handbag | H12: Accessories | I12: 1899 | J12: 2 | K12: 0.14 | L12: UPI | M12: Online | N12: Delivered | O12: 4.5 | P12: =I12*J12 -> 3798 | Q12: =P12*K12 -> 531.72 | R12: =P12-Q12 -> 3266.28 | S12: =IF(OR(N12="Cancelled",N12="Returned"),0,R12) -> 3266.28 | T12: =IF(R12>=4000,"High",IF(R12>=2500,"Medium","Low")) -> Medium | U12: =IF(K12>=15%,"15%+",IF(K12>=10%,"10-14%","Under 10%")) -> 10-14% | V12: =IF(OR(N12="Cancelled",N12="Returned"),"Lost",IF(N12="Shipped","In Transit","Completed")) -> Completed | W12: =IF(O12=0,"Missing",IF(O12>=4.5,"Excellent",IF(O12>=4,"Good","Poor"))) -> Excellent | X12: =IF(AND(R12>AVERAGE($R$2:$R$36),O12>=4.5,V12<>"Lost"),"Key Customer",IF(AND(V12="Lost",R12>AVERAGE($R$2:$R$36)),"Win Back",IF(V12="Lost","Follow Up","Regular"))) -> Key Customer
A13: ORD1012 | B13: 46240 | C13: C012 | D13: Srilatha | E13: Mumbai | F13: Electronics | G13: Smart Watch | H13: Wearables | I13: 4999 | J13: 1 | K13: 0.25 | L13: Card | M13: Online | N13: Delivered | O13: 4.8 | P13: =I13*J13 -> 4999 | Q13: =P13*K13 -> 1249.75 | R13: =P13-Q13 -> 3749.25 | S13: =IF(OR(N13="Cancelled",N13="Returned"),0,R13) -> 3749.25 | T13: =IF(R13>=4000,"High",IF(R13>=2500,"Medium","Low")) -> Medium | U13: =IF(K13>=15%,"15%+",IF(K13>=10%,"10-14%","Under 10%")) -> 15%+ | V13: =IF(OR(N13="Cancelled",N13="Returned"),"Lost",IF(N13="Shipped","In Transit","Completed")) -> Completed | W13: =IF(O13=0,"Missing",IF(O13>=4.5,"Excellent",IF(O13>=4,"Good","Poor"))) -> Excellent | X13: =IF(AND(R13>AVERAGE($R$2:$R$36),O13>=4.5,V13<>"Lost"),"Key Customer",IF(AND(V13="Lost",R13>AVERAGE($R$2:$R$36)),"Win Back",IF(V13="Lost","Follow Up","Regular"))) -> Key Customer
... A36: ORD1035 | B36: 46252 | C36: C035 | D36: Gautham | E36: Pune | F36: Home & Kitchen | G36: Toaster | H36: Not Available | I36: 2299 | J36: 1 | K36: 0.14 | L36: Card | M36: Online | N36: Returned | O36: 3.1 | P36: =I36*J36 -> 2299 | Q36: =P36*K36 -> 321.86 | R36: =P36-Q36 -> 1977.14 | S36: =IF(OR(N36="Cancelled",N36="Returned"),0,R36) -> 0 | T36: =IF(R36>=4000,"High",IF(R36>=2500,"Medium","Low")) -> Low | U36: =IF(K36>=15%,"15%+",IF(K36>=10%,"10-14%","Under 10%")) -> 10-14% | V36: =IF(OR(N36="Cancelled",N36="Returned"),"Lost",IF(N36="Shipped","In Transit","Completed")) -> Lost | W36: =IF(O36=0,"Missing",IF(O36>=4.5,"Excellent",IF(O36>=4,"Good","Poor"))) -> Poor | X36: =IF(AND(R36>AVERAGE($R$2:$R$36),O36>=4.5,V36<>"Lost"),"Key Customer",IF(AND(V36="Lost",R36>AVERAGE($R$2:$R$36)),"Win Back",IF(V36="Lost","Follow Up","Regular"))) -> Follow Up
A38: Notes: Customer Rating 0 = rating missing (flagged "Missing" in Rating Check, excluded from average ratings). Subcategory "Not Available" is kept as in the source data. Blue = original data; black = formulas.

Sheet Pivot Summary
A1: Pivot Summary – Retail Sales, August 2026
A2: All figures are formulas (SUMIFS / COUNTIFS / AVERAGEIFS) linked to the Data sheet. Ratings of 0 (missing) are excluded from averages.
A4: Key figures
A5: Total orders | B5: =COUNTA(Data!$A$2:$A$36) -> 35
A6: Booked net sales (INR) | B6: =SUM(Data!$R$2:$R$36) -> 102458.91
A7: Realised net sales (INR) | B7: =SUM(Data!$S$2:$S$36) -> 71013.78
A8: Lost to cancellations / returns (INR) | B8: =B6-B7 -> 31445.13
A9: Share of booked sales lost | B9: =IFERROR(B8/B6,0) -> 0.30690479
A10: Lost orders (cancelled + returned) | B10: =COUNTIF(Data!$V$2:$V$36,"Lost") -> 11
A11: Average order value (INR) | B11: =IFERROR(B6/B5,0) -> 2927.3974
A12: Average customer rating | B12: =AVERAGEIF(Data!$O$2:$O$36,">0") -> 4.2617647
A14: By Category
A15: Value | B15: Orders | C15: Booked Sales | D15: Realised Sales | E15: Lost Sales | F15: % Lost | G15: Lost Orders | H15: Avg Rating | I15: Share of Booked
A16: Electronics | B16: =COUNTIF(Data!$F$2:$F$36,A16) -> 9 | C16: =SUMIFS(Data!$R$2:$R$36,Data!$F$2:$F$36,A16) -> 34559.24 | D16: =SUMIFS(Data!$S$2:$S$36,Data!$F$2:$F$36,A16) -> 20464.27 | E16: =C16-D16 -> 14094.97 | F16: =IFERROR(E16/C16,0) -> 0.40784954 | G16: =COUNTIFS(Data!$F$2:$F$36,A16,Data!$V$2:$V$36,"Lost") -> 4 | H16: =IFERROR(AVERAGEIFS(Data!$O$2:$O$36,Data!$F$2:$F$36,A16,Data!$O$2:$O$36,">0"),0) -> 4.55 | I16: =IFERROR(C16/$B$6,0) -> 0.33729853
A17: Fashion | B17: =COUNTIF(Data!$F$2:$F$36,A17) -> 8 | C17: =SUMIFS(Data!$R$2:$R$36,Data!$F$2:$F$36,A17) -> 23224.81 | D17: =SUMIFS(Data!$S$2:$S$36,Data!$F$2:$F$36,A17) -> 17949.71 | E17: =C17-D17 -> 5275.1 | F17: =IFERROR(E17/C17,0) -> 0.22713211 | G17: =COUNTIFS(Data!$F$2:$F$36,A17,Data!$V$2:$V$36,"Lost") -> 2 | H17: =IFERROR(AVERAGEIFS(Data!$O$2:$O$36,Data!$F$2:$F$36,A17,Data!$O$2:$O$36,">0"),0) -> 4.3875 | I17: =IFERROR(C17/$B$6,0) -> 0.22667438
A18: Home & Kitchen | B18: =COUNTIF(Data!$F$2:$F$36,A18) -> 7 | C18: =SUMIFS(Data!$R$2:$R$36,Data!$F$2:$F$36,A18) -> 20261.15 | D18: =SUMIFS(Data!$S$2:$S$36,Data!$F$2:$F$36,A18) -> 15344.85 | E18: =C18-D18 -> 4916.3 | F18: =IFERROR(E18/C18,0) -> 0.24264664 | G18: =COUNTIFS(Data!$F$2:$F$36,A18,Data!$V$2:$V$36,"Lost") -> 2 | H18: =IFERROR(AVERAGEIFS(Data!$O$2:$O$36,Data!$F$2:$F$36,A18,Data!$O$2:$O$36,">0"),0) -> 3.9142857 | I18: =IFERROR(C18/$B$6,0) -> 0.19774903
A19: Grocery | B19: =COUNTIF(Data!$F$2:$F$36,A19) -> 6 | C19: =SUMIFS(Data!$R$2:$R$36,Data!$F$2:$F$36,A19) -> 13856.74 | D19: =SUMIFS(Data!$S$2:$S$36,Data!$F$2:$F$36,A19) -> 11386.74 | E19: =C19-D19 -> 2470 | F19: =IFERROR(E19/C19,0) -> 0.1782526 | G19: =COUNTIFS(Data!$F$2:$F$36,A19,Data!$V$2:$V$36,"Lost") -> 1 | H19: =IFERROR(AVERAGEIFS(Data!$O$2:$O$36,Data!$F$2:$F$36,A19,Data!$O$2:$O$36,">0"),0) -> 4.0166667 | I19: =IFERROR(C19/$B$6,0) -> 0.13524192
A20: Beauty | B20: =COUNTIF(Data!$F$2:$F$36,A20) -> 5 | C20: =SUMIFS(Data!$R$2:$R$36,Data!$F$2:$F$36,A20) -> 10556.97 | D20: =SUMIFS(Data!$S$2:$S$36,Data!$F$2:$F$36,A20) -> 5868.21 | E20: =C20-D20 -> 4688.76 | F20: =IFERROR(E20/C20,0) -> 0.4441388 | G20: =COUNTIFS(Data!$F$2:$F$36,A20,Data!$V$2:$V$36,"Lost") -> 2 | H20: =IFERROR(AVERAGEIFS(Data!$O$2:$O$36,Data!$F$2:$F$36,A20,Data!$O$2:$O$36,">0"),0) -> 4.38 | I20: =IFERROR(C20/$B$6,0) -> 0.10303613
A21: Total | B21: =SUM(B16:B20) -> 35 | C21: =SUM(C16:C20) -> 102458.91 | D21: =SUM(D16:D20) -> 71013.78 | E21: =SUM(E16:E20) -> 31445.13 | F21: =IFERROR(E21/C21,0) -> 0.30690479 | G21: =SUM(G16:G20) -> 11 | H21: =AVERAGEIF(Data!$O$2:$O$36,">0") -> 4.2617647 | I21: =IFERROR(C21/$B$6,0) -> 1
A24: By City
A25: Value | B25: Orders | C25: Booked Sales | D25: Realised Sales | E25: Lost Sales | F25: % Lost | G25: Lost Orders | H25: Avg Rating | I25: Share of Booked
A26: Bangalore | B26: =COUNTIF(Data!$E$2:$E$36,A26) -> 7 | C26: =SUMIFS(Data!$R$2:$R$36,Data!$E$2:$E$36,A26) -> 24308.51 | D26: =SUMIFS(Data!$S$2:$S$36,Data!$E$2:$E$36,A26) -> 17977.79 | E26: =C26-D26 -> 6330.72 | F26: =IFERROR(E26/C26,0) -> 0.26043225 | G26: =COUNTIFS(Data!$E$2:$E$36,A26,Data!$V$2:$V$36,"Lost") -> 2 | H26: =IFERROR(AVERAGEIFS(Data!$O$2:$O$36,Data!$E$2:$E$36,A26,Data!$O$2:$O$36,">0"),0) -> 4.4857143 | I26: =IFERROR(C26/$B$6,0) -> 0.2372513
A27: Mumbai | B27: =COUNTIF(Data!$E$2:$E$36,A27) -> 5 | C27: =SUMIFS(Data!$R$2:$R$36,Data!$E$2:$E$36,A27) -> 16496.31 | D27: =SUMIFS(Data!$S$2:$S$36,Data!$E$2:$E$36,A27) -> 11557.95 | E27: =C27-D27 -> 4938.36 | F27: =IFERROR(E27/C27,0) -> 0.29936149 | G27: =COUNTIFS(Data!$E$2:$E$36,A27,Data!$V$2:$V$36,"Lost") -> 2 | H27: =IFERROR(AVERAGEIFS(Data!$O$2:$O$36,Data!$E$2:$E$36,A27,Data!$O$2:$O$36,">0"),0) -> 4.16 | I27: =IFERROR(C27/$B$6,0) -> 0.16100415
A28: Hyderabad | B28: =COUNTIF(Data!$E$2:$E$36,A28) -> 6 | C28: =SUMIFS(Data!$R$2:$R$36,Data!$E$2:$E$36,A28) -> 16330.94 | D28: =SUMIFS(Data!$S$2:$S$36,Data!$E$2:$E$36,A28) -> 14102.66 | E28: =C28-D28 -> 2228.28 | F28: =IFERROR(E28/C28,0) -> 0.1364453 | G28: =COUNTIFS(Data!$E$2:$E$36,A28,Data!$V$2:$V$36,"Lost") -> 1 | H28: =IFERROR(AVERAGEIFS(Data!$O$2:$O$36,Data!$E$2:$E$36,A28,Data!$O$2:$O$36,">0"),0) -> 4.1166667 | I28: =IFERROR(C28/$B$6,0) -> 0.15939014
A29: Chennai | B29: =COUNTIF(Data!$E$2:$E$36,A29) -> 6 | C29: =SUMIFS(Data!$R$2:$R$36,Data!$E$2:$E$36,A29) -> 16011.31 | D29: =SUMIFS(Data!$S$2:$S$36,Data!$E$2:$E$36,A29) -> 12809.09 | E29: =C29-D29 -> 3202.22 | F29: =IFERROR(E29/C29,0) -> 0.19999738 | G29: =COUNTIFS(Data!$E$2:$E$36,A29,Data!$V$2:$V$36,"Lost") -> 1 | H29: =IFERROR(AVERAGEIFS(Data!$O$2:$O$36,Data!$E$2:$E$36,A29,Data!$O$2:$O$36,">0"),0) -> 4.3666667 | I29: =IFERROR(C29/$B$6,0) -> 0.15627055
A30: Pune | B30: =COUNTIF(Data!$E$2:$E$36,A30) -> 6 | C30: =SUMIFS(Data!$R$2:$R$36,Data!$E$2:$E$36,A30) -> 15778.75 | D30: =SUMIFS(Data!$S$2:$S$36,Data!$E$2:$E$36,A30) -> 4657.41 | E30: =C30-D30 -> 11121.34 | F30: =IFERROR(E30/C30,0) -> 0.70483023 | G30: =COUNTIFS(Data!$E$2:$E$36,A30,Data!$V$2:$V$36,"Lost") -> 4 | H30: =IFERROR(AVERAGEIFS(Data!$O$2:$O$36,Data!$E$2:$E$36,A30,Data!$O$2:$O$36,">0"),0) -> 4.12 | I30: =IFERROR(C30/$B$6,0) -> 0.15400076
A31: Delhi | B31: =COUNTIF(Data!$E$2:$E$36,A31) -> 5 | C31: =SUMIFS(Data!$R$2:$R$36,Data!$E$2:$E$36,A31) -> 13533.09 | D31: =SUMIFS(Data!$S$2:$S$36,Data!$E$2:$E$36,A31) -> 9908.88 | E31: =C31-D31 -> 3624.21 | F31: =IFERROR(E31/C31,0) -> 0.26780358 | G31: =COUNTIFS(Data!$E$2:$E$36,A31,Data!$V$2:$V$36,"Lost") -> 1 | H31: =IFERROR(AVERAGEIFS(Data!$O$2:$O$36,Data!$E$2:$E$36,A31,Data!$O$2:$O$36,">0"),0) -> 4.24 | I31: =IFERROR(C31/$B$6,0) -> 0.1320831
A32: Total | B32: =SUM(B26:B31) -> 35 | C32: =SUM(C26:C31) -> 102458.91 | D32: =SUM(D26:D31) -> 71013.78 | E32: =SUM(E26:E31) -> 31445.13 | F32: =IFERROR(E32/C32,0) -> 0.30690479 | G32: =SUM(G26:G31) -> 11 | H32: =AVERAGEIF(Data!$O$2:$O$36,">0") -> 4.2617647 | I32: =IFERROR(C32/$B$6,0) -> 1
A35: By Sales Channel
A36: Value | B36: Orders | C36: Booked Sales | D36: Realised Sales | E36: Lost Sales | F36: % Lost | G36: Lost Orders | H36: Avg Rating | I36: Share of Booked
A37: Online | B37: =COUNTIF(Data!$M$2:$M$36,A37) -> 22 | C37: =SUMIFS(Data!$R$2:$R$36,Data!$M$2:$M$36,A37) -> 69382.75 | D37: =SUMIFS(Data!$S$2:$S$36,Data!$M$2:$M$36,A37) -> 46144 | E37: =C37-D37 -> 23238.75 | F37: =IFERROR(E37/C37,0) -> 0.33493556 | G37: =COUNTIFS(Data!$M$2:$M$36,A37,Data!$V$2:$V$36,"Lost") -> 8 | H37: =IFERROR(AVERAGEIFS(Data!$O$2:$O$36,Data!$M$2:$M$36,A37,Data!$O$2:$O$36,">0"),0) -> 4.2666667 | I37: =IFERROR(C37/$B$6,0) -> 0.67717634
A38: Store | B38: =COUNTIF(Data!$M$2:$M$36,A38) -> 13 | C38: =SUMIFS(Data!$R$2:$R$36,Data!$M$2:$M$36,A38) -> 33076.16 | D38: =SUMIFS(Data!$S$2:$S$36,Data!$M$2:$M$36,A38) -> 24869.78 | E38: =C38-D38 -> 8206.38 | F38: =IFERROR(E38/C38,0) -> 0.24810558 | G38: =COUNTIFS(Data!$M$2:$M$36,A38,Data!$V$2:$V$36,"Lost") -> 3 | H38: =IFERROR(AVERAGEIFS(Data!$O$2:$O$36,Data!$M$2:$M$36,A38,Data!$O$2:$O$36,">0"),0) -> 4.2538462 | I38: =IFERROR(C38/$B$6,0) -> 0.32282366
A39: Total | B39: =SUM(B37:B38) -> 35 | C39: =SUM(C37:C38) -> 102458.91 | D39: =SUM(D37:D38) -> 71013.78 | E39: =SUM(E37:E38) -> 31445.13 | F39: =IFERROR(E39/C39,0) -> 0.30690479 | G39: =SUM(G37:G38) -> 11 | H39: =AVERAGEIF(Data!$O$2:$O$36,">0") -> 4.2617647 | I39: =IFERROR(C39/$B$6,0) -> 1
A42: By Discount Band
A43: Value | B43: Orders | C43: Booked Sales | D43: Realised Sales | E43: Lost Sales | F43: % Lost | G43: Lost Orders | H43: Avg Rating | I43: Share of Booked
A44: Under 10% | B44: =COUNTIF(Data!$U$2:$U$36,A44) -> 12 | C44: =SUMIFS(Data!$R$2:$R$36,Data!$U$2:$U$36,A44) -> 30021.54 | D44: =SUMIFS(Data!$S$2:$S$36,Data!$U$2:$U$36,A44) -> 21699.05 | E44: =C44-D44 -> 8322.49 | F44: =IFERROR(E44/C44,0) -> 0.27721729 | G44: =COUNTIFS(Data!$U$2:$U$36,A44,Data!$V$2:$V$36,"Lost") -> 3 | H44: =IFERROR(AVERAGEIFS(Data!$O$2:$O$36,Data!$U$2:$U$36,A44,Data!$O$2:$O$36,">0"),0) -> 4.1333333 | I44: =IFERROR(C44/$B$6,0) -> 0.29301053
A45: 10-14% | B45: =COUNTIF(Data!$U$2:$U$36,A45) -> 11 | C45: =SUMIFS(Data!$R$2:$R$36,Data!$U$2:$U$36,A45) -> 30515.47 | D45: =SUMIFS(Data!$S$2:$S$36,Data!$U$2:$U$36,A45) -> 19005.39 | E45: =C45-D45 -> 11510.08 | F45: =IFERROR(E45/C45,0) -> 0.37718836 | G45: =COUNTIFS(Data!$U$2:$U$36,A45,Data!$V$2:$V$36,"Lost") -> 4 | H45: =IFERROR(AVERAGEIFS(Data!$O$2:$O$36,Data!$U$2:$U$36,A45,Data!$O$2:$O$36,">0"),0) -> 4.3545455 | I45: =IFERROR(C45/$B$6,0) -> 0.2978313
A46: 15%+ | B46: =COUNTIF(Data!$U$2:$U$36,A46) -> 12 | C46: =SUMIFS(Data!$R$2:$R$36,Data!$U$2:$U$36,A46) -> 41921.9 | D46: =SUMIFS(Data!$S$2:$S$36,Data!$U$2:$U$36,A46) -> 30309.34 | E46: =C46-D46 -> 11612.56 | F46: =IFERROR(E46/C46,0) -> 0.27700462 | G46: =COUNTIFS(Data!$U$2:$U$36,A46,Data!$V$2:$V$36,"Lost") -> 4 | H46: =IFERROR(AVERAGEIFS(Data!$O$2:$O$36,Data!$U$2:$U$36,A46,Data!$O$2:$O$36,">0"),0) -> 4.3090909 | I46: =IFERROR(C46/$B$6,0) -> 0.40915817
A47: Total | B47: =SUM(B44:B46) -> 35 | C47: =SUM(C44:C46) -> 102458.91 | D47: =SUM(D44:D46) -> 71013.78 | E47: =SUM(E44:E46) -> 31445.13 | F47: =IFERROR(E47/C47,0) -> 0.30690479 | G47: =SUM(G44:G46) -> 11 | H47: =AVERAGEIF(Data!$O$2:$O$36,">0") -> 4.2617647 | I47: =IFERROR(C47/$B$6,0) -> 1
A49: Tip: to show a native PivotTable too, select Data!A1:X36 → Insert → PivotTable → rows = Category, values = Net Sales and Realised Sales.

Sheet Insights
A1: Insights and recommendations
A3: # | B3: Finding | C3: Key number | D3: Recommendation
A4: 1 | B4: Almost a third of booked sales never turn into revenue because orders are cancelled or returned. | C4: ='Pivot Summary'!B9 -> 0.30690479 | D4: Find out why orders are cancelled (delivery time, price, stock) before spending more on new customers.
A5: 2 | B5: Electronics is the biggest category (about a third of booked sales), but it also loses the most money: 4 of its 9 orders were cancelled or returned. | C5: ='Pivot Summary'!E16 -> 14094.97 | D5: Check Electronics stock and delivery promises; a small drop in cancellations here has the biggest effect.
A6: 3 | B6: Pune loses the largest share of its booked sales of all six cities. | C6: =INDEX('Pivot Summary'!F26:F31,MATCH("Pune",'Pivot Summary'!A26:A31,0)) -> 0.70483023 | D6: Review Pune orders one by one; look for a common cause such as one courier, store or product.
A7: 4 | B7: Heavy discounts do not stop cancellations: 1 in 3 orders with 15%+ discount was still lost, compared with 1 in 4 orders under 10%. | C7: =IFERROR('Pivot Summary'!G46/'Pivot Summary'!B46,0) -> 0.33333333 | D7: Test smaller discounts on a few products; with only 35 orders this is a signal to check, not a proof.
A8: 5 | B8: Data quality: several orders have no subcategory and one order has no rating. | C8: =COUNTIF(Data!H2:H36,"Not Available") -> 13 | D8: Make subcategory and rating required fields when orders are entered.
B10: Key number for #1 = share of booked sales lost; #2 = Electronics lost sales in INR; #3 = share of Pune booked sales lost; #4 = lost-order rate for the 15%+ discount band; #5 = orders with subcategory "Not Available".
